LICENSE
MANIFEST.in
README.rst
pyproject.toml
setup.cfg
setup.py
atatus/__init__.py
atatus/base.py
atatus/events.py
atatus/middleware.py
atatus/processors.py
atatus/py.typed
atatus/traces.py
atatus/version.py
atatus.egg-info/PKG-INFO
atatus.egg-info/SOURCES.txt
atatus.egg-info/dependency_links.txt
atatus.egg-info/entry_points.txt
atatus.egg-info/not-zip-safe
atatus.egg-info/requires.txt
atatus.egg-info/top_level.txt
atatus/collector/__init__.py
atatus/collector/base.py
atatus/collector/builder.py
atatus/collector/hist.py
atatus/collector/layer.py
atatus/collector/transport.py
atatus/conf/__init__.py
atatus/conf/constants.py
atatus/context/__init__.py
atatus/context/base.py
atatus/context/contextvars.py
atatus/context/threadlocal.py
atatus/contrib/__init__.py
atatus/contrib/asgi.py
atatus/contrib/paste.py
atatus/contrib/aiohttp/__init__.py
atatus/contrib/aiohttp/middleware.py
atatus/contrib/aiohttp/utils.py
atatus/contrib/asyncio/__init__.py
atatus/contrib/asyncio/traces.py
atatus/contrib/celery/__init__.py
atatus/contrib/django/__init__.py
atatus/contrib/django/apps.py
atatus/contrib/django/client.py
atatus/contrib/django/context_processors.py
atatus/contrib/django/handlers.py
atatus/contrib/django/utils.py
atatus/contrib/django/celery/__init__.py
atatus/contrib/django/celery/models.py
atatus/contrib/django/management/__init__.py
atatus/contrib/django/management/commands/__init__.py
atatus/contrib/django/management/commands/atatus.py
atatus/contrib/django/middleware/__init__.py
atatus/contrib/django/middleware/wsgi.py
atatus/contrib/flask/__init__.py
atatus/contrib/flask/utils.py
atatus/contrib/grpc/__init__.py
atatus/contrib/grpc/async_server_interceptor.py
atatus/contrib/grpc/client_interceptor.py
atatus/contrib/grpc/server_interceptor.py
atatus/contrib/grpc/utils.py
atatus/contrib/opentelemetry/__init__.py
atatus/contrib/opentelemetry/context.py
atatus/contrib/opentelemetry/span.py
atatus/contrib/opentelemetry/trace.py
atatus/contrib/opentelemetry/utils.py
atatus/contrib/opentracing/__init__.py
atatus/contrib/opentracing/span.py
atatus/contrib/opentracing/tracer.py
atatus/contrib/pylons/__init__.py
atatus/contrib/rq/__init__.py
atatus/contrib/sanic/__init__.py
