Metadata-Version: 2.1
Name: atatus
Version: 2.0.0
Summary: Atatus Python Agent
Home-page: https://www.atatus.com
Author: Atatus
License: BSD
Project-URL: Documentation, https://docs.atatus.com/docs/application-monitoring/python-agent/overview.html
Project-URL: Release notes, https://docs.atatus.com/docs/release-notes/python.html
Platform: UNKNOWN
Classifier: Intended Audience :: Developers
Classifier: Intended Audience :: System Administrators
Classifier: Operating System :: OS Independent
Classifier: Topic :: Software Development
Classifier: Programming Language :: Python
Classifier: Programming Language :: Python :: 3.6
Classifier: Programming Language :: Python :: 3.7
Classifier: Programming Language :: Python :: 3.8
Classifier: Programming Language :: Python :: 3.9
Classifier: Programming Language :: Python :: 3.10
Classifier: Programming Language :: Python :: 3.11
Classifier: Programming Language :: Python :: 3.12
Classifier: Programming Language :: Python :: Implementation :: CPython
Classifier: Programming Language :: Python :: Implementation :: PyPy
Requires-Python: <4,>=3.6
Provides-Extra: flask
Provides-Extra: aiohttp
Provides-Extra: tornado
Provides-Extra: starlette
Provides-Extra: opentracing
Provides-Extra: sanic
Provides-Extra: opentelemetry
